zuper_graphs.pyi
zuper_graphs.cpython-310-x86_64-linux-gnu.so
zuper_graphs_draw.pyi
zuper_graphs_draw.cpython-310-x86_64-linux-gnu.so
zuper_graphs_z7-7.3.2202061117.dist-info/WHEEL
zuper_graphs_z7-7.3.2202061117.dist-info/top_level.txt
zuper_graphs_z7-7.3.2202061117.dist-info/RECORD
zuper_graphs_z7-7.3.2202061117.dist-info/METADATA
zuper_graphs_z7-7.3.2202061117.dist-info/zip-safe
